{
	"format_version": "1.8.0",
	"animations": {
		"animation.metal_gear_rex.display_pose": {
			"animation_length": 0.08333,
			"bones": {
				"main": {
					"position": [0, 32, 0]
				},
				"gattling_gun": {
					"rotation": [0, -27.5, 0]
				},
				"weapon_pack": {
					"rotation": [-12.5, 0, 0]
				},
				"radome": {
					"rotation": [20, 5, 0]
				},
				"railgun": {
					"rotation": [-7.5, 7.5, -12.5]
				},
				"neck": {
					"rotation": [25, 0, 0]
				},
				"head": {
					"rotation": [-10, 0, 7.5]
				},
				"right_leg": {
					"rotation": [-0.66584, 9.88744, -7.68615]
				},
				"right_knee_joint": {
					"rotation": [-45, 0, 0]
				},
				"right_knee": {
					"rotation": [-10, 0, 0]
				},
				"right_leg_telescopic": {
					"position": [0, 0, -8]
				},
				"right_outer_toe": {
					"rotation": [-30, 0, 0]
				},
				"right_inner_toe": {
					"rotation": [-30, 0, 0]
				},
				"right_foot": {
					"rotation": [-37.5, 0, 0]
				},
				"left_leg": {
					"rotation": [-3.36212, -21.48944, 17.58347]
				},
				"left_leg_lower": {
					"position": [0, 0, 0]
				},
				"left_knee_joint": {
					"rotation": [-42.5, 0, 0]
				},
				"left_knee": {
					"rotation": [-12.5, 0, 0]
				},
				"left_leg_telescopic": {
					"position": [0, 0, -8]
				},
				"left_outer_toe": {
					"rotation": [-27.5, 0, 0]
				},
				"left_inner_toe": {
					"rotation": [-30, 0, 0]
				},
				"left_foot": {
					"rotation": [-37.5, 0, 0]
				},
				"left_thigh": {
					"rotation": [22.5, -7.5, 0]
				},
				"knee_left": {
					"rotation": [15, 0, 0]
				},
				"right_thigh": {
					"rotation": [22.5, 10, 0]
				},
				"knee_right": {
					"rotation": [15, 0, 0]
				}
			}
		},
		"animation.rex.inactive": {
			"loop": true,
			"bones": {
				"main": {
					"position": [0, 0, 27]
				}
			}
		},
		"animation.rex.fire_railgun": {
			"loop": true,
			"animation_length": 1,
			"bones": {
				"main": {
					"position": {
						"0.0": [0, 37, 0],
						"0.0417": [0, 37.15, 2.41],
						"0.0833": [0, 37.3, 5.81],
						"0.125": [0, 37, 9],
						"0.1667": [0, 35.67, 12.33],
						"0.2083": [0, 33.89, 15.44],
						"0.25": [0, 33, 16],
						"0.2917": [0, 33.03, 15.66],
						"0.3333": [0, 33.12, 15.14],
						"0.375": [0, 33.25, 14.48],
						"0.4167": [0, 33.43, 13.68],
						"0.4583": [0, 33.64, 12.78],
						"0.5": [0, 33.89, 11.78],
						"0.5417": [0, 34.16, 10.71],
						"0.5833": [0, 34.45, 9.59],
						"0.625": [0, 34.75, 8.44],
						"0.6667": [0, 35.06, 7.28],
						"0.7083": [0, 35.37, 6.12],
						"0.75": [0, 35.67, 5],
						"0.7917": [0, 35.96, 3.93],
						"0.8333": [0, 36.23, 2.92],
						"0.875": [0, 36.47, 2.01],
						"0.9167": [0, 36.69, 1.2],
						"0.9583": [0, 36.87, 0.53],
						"1.0": [0, 37, 0]
					}
				},
				"body": {
					"rotation": {
						"0.0": [0, 0, 0],
						"0.0417": [0.46, 0, 0],
						"0.0833": [0.93, 0, 0],
						"0.125": [0, 0, 0],
						"0.1667": [-4.17, 0, 0],
						"0.2083": [-9.72, 0, 0],
						"0.25": [-12.5, 0, 0],
						"0.2917": [-12.41, 0, 0],
						"0.3333": [-12.14, 0, 0],
						"0.375": [-11.72, 0, 0],
						"0.4167": [-11.16, 0, 0],
						"0.4583": [-10.49, 0, 0],
						"0.5": [-9.72, 0, 0],
						"0.5417": [-8.88, 0, 0],
						"0.5833": [-7.97, 0, 0],
						"0.625": [-7.03, 0, 0],
						"0.6667": [-6.07, 0, 0],
						"0.7083": [-5.11, 0, 0],
						"0.75": [-4.17, 0, 0],
						"0.7917": [-3.26, 0, 0],
						"0.8333": [-2.42, 0, 0],
						"0.875": [-1.65, 0, 0],
						"0.9167": [-0.98, 0, 0],
						"0.9583": [-0.42, 0, 0],
						"1.0": [0, 0, 0]
					}
				},
				"weapon_pack": {
					"rotation": [-7.5, 0, 0]
				},
				"radome": {
					"rotation": [10, 0, 0]
				},
				"railgun": {
					"rotation": {
						"0.0": [-10, -5, 0],
						"0.0417": [-8.8, -5, 0],
						"0.0833": [-7.59, -5, 0],
						"0.125": [-10, -5, 0],
						"0.1667": [-20.83, -5, 0],
						"0.2083": [-35.28, -5, 0],
						"0.25": [-42.5, -5, 0],
						"0.2917": [-42.26, -5, 0],
						"0.3333": [-41.56, -5, 0],
						"0.375": [-40.47, -5, 0],
						"0.4167": [-39.02, -5, 0],
						"0.4583": [-37.28, -5, 0],
						"0.5": [-35.28, -5, 0],
						"0.5417": [-33.08, -5, 0],
						"0.5833": [-30.73, -5, 0],
						"0.625": [-28.28, -5, 0],
						"0.6667": [-25.78, -5, 0],
						"0.7083": [-23.28, -5, 0],
						"0.75": [-20.83, -5, 0],
						"0.7917": [-18.48, -5, 0],
						"0.8333": [-16.29, -5, 0],
						"0.875": [-14.29, -5, 0],
						"0.9167": [-12.54, -5, 0],
						"0.9583": [-11.1, -5, 0],
						"1.0": [-10, -5, 0]
					}
				},
				"neck": {
					"rotation": [5, 0, 0]
				},
				"head": {
					"rotation": [10, 0, 0]
				},
				"left_thigh": {
					"rotation": {
						"0.0": [30, 0, 0],
						"0.0417": [28.7, 0, 0],
						"0.0833": [26.85, 0, 0],
						"0.125": [25, 0, 0],
						"0.1667": [22.78, 0, 0],
						"0.2083": [20.56, 0, 0],
						"0.25": [20, 0, 0],
						"0.2917": [20.2, 0, 0],
						"0.3333": [20.51, 0, 0],
						"0.375": [20.91, 0, 0],
						"0.4167": [21.41, 0, 0],
						"0.4583": [21.97, 0, 0],
						"0.5": [22.59, 0, 0],
						"0.5417": [23.26, 0, 0],
						"0.5833": [23.96, 0, 0],
						"0.625": [24.69, 0, 0],
						"0.6667": [25.42, 0, 0],
						"0.7083": [26.14, 0, 0],
						"0.75": [26.85, 0, 0],
						"0.7917": [27.53, 0, 0],
						"0.8333": [28.16, 0, 0],
						"0.875": [28.74, 0, 0],
						"0.9167": [29.25, 0, 0],
						"0.9583": [29.67, 0, 0],
						"1.0": [30, 0, 0]
					}
				},
				"knee_left": {
					"rotation": {
						"0.0": [10, 0, 0],
						"0.0417": [10, 0, 0],
						"0.0833": [10, 0, 0],
						"0.125": [10, 0, 0],
						"0.1667": [10, 0, 0],
						"0.2083": [10, 0, 0],
						"0.25": [10, 0, 0],
						"0.2917": [10, 0, 0],
						"0.3333": [10, 0, 0],
						"0.375": [10, 0, 0],
						"0.4167": [10, 0, 0],
						"0.4583": [10, 0, 0],
						"0.5": [10, 0, 0],
						"0.5417": [10, 0, 0],
						"0.5833": [10, 0, 0],
						"0.625": [10, 0, 0],
						"0.6667": [10, 0, 0],
						"0.7083": [10, 0, 0],
						"0.75": [10, 0, 0],
						"0.7917": [10, 0, 0],
						"0.8333": [10, 0, 0],
						"0.875": [10, 0, 0],
						"0.9167": [10, 0, 0],
						"0.9583": [10, 0, 0],
						"1.0": [10, 0, 0]
					}
				},
				"left_leg": {
					"rotation": [0, 0, 0]
				},
				"left_heel_joint": {
					"rotation": [-37.5, 0, 0]
				},
				"left_knee": {
					"rotation": [-15, 0, 0]
				},
				"left_leg_telescopic": {
					"position": {
						"0.0": [0, 0, -10],
						"0.0417": [0, 0, -11.33],
						"0.0833": [0, 0, -13.11],
						"0.125": [0, 0, -14],
						"0.1667": [0, 0, -13.98],
						"0.2083": [0, 0, -13.91],
						"0.25": [0, 0, -13.81],
						"0.2917": [0, 0, -13.68],
						"0.3333": [0, 0, -13.51],
						"0.375": [0, 0, -13.32],
						"0.4167": [0, 0, -13.11],
						"0.4583": [0, 0, -12.88],
						"0.5": [0, 0, -12.64],
						"0.5417": [0, 0, -12.38],
						"0.5833": [0, 0, -12.12],
						"0.625": [0, 0, -11.85],
						"0.6667": [0, 0, -11.59],
						"0.7083": [0, 0, -11.33],
						"0.75": [0, 0, -11.08],
						"0.7917": [0, 0, -10.85],
						"0.8333": [0, 0, -10.63],
						"0.875": [0, 0, -10.43],
						"0.9167": [0, 0, -10.26],
						"0.9583": [0, 0, -10.11],
						"1.0": [0, 0, -10]
					}
				},
				"left_outer_toe": {
					"rotation": [-15, 0, 0]
				},
				"left_inner_toe": {
					"rotation": [-17.5, 0, 0]
				},
				"left_foot": {
					"rotation": {
						"0.0": [-40, 0, 0],
						"0.0417": [-38.7, 0, 0],
						"0.0833": [-36.85, 0, 0],
						"0.125": [-35, 0, 0],
						"0.1667": [-32.78, 0, 0],
						"0.2083": [-30.56, 0, 0],
						"0.25": [-30, 0, 0],
						"0.2917": [-30.2, 0, 0],
						"0.3333": [-30.51, 0, 0],
						"0.375": [-30.91, 0, 0],
						"0.4167": [-31.41, 0, 0],
						"0.4583": [-31.97, 0, 0],
						"0.5": [-32.59, 0, 0],
						"0.5417": [-33.26, 0, 0],
						"0.5833": [-33.96, 0, 0],
						"0.625": [-34.69, 0, 0],
						"0.6667": [-35.42, 0, 0],
						"0.7083": [-36.14, 0, 0],
						"0.75": [-36.85, 0, 0],
						"0.7917": [-37.53, 0, 0],
						"0.8333": [-38.16, 0, 0],
						"0.875": [-38.74, 0, 0],
						"0.9167": [-39.25, 0, 0],
						"0.9583": [-39.67, 0, 0],
						"1.0": [-40, 0, 0]
					}
				},
				"right_thigh": {
					"rotation": {
						"0.0": [30, 0, 0],
						"0.0417": [28.7, 0, 0],
						"0.0833": [26.85, 0, 0],
						"0.125": [25, 0, 0],
						"0.1667": [22.78, 0, 0],
						"0.2083": [20.56, 0, 0],
						"0.25": [20, 0, 0],
						"0.2917": [20.2, 0, 0],
						"0.3333": [20.51, 0, 0],
						"0.375": [20.91, 0, 0],
						"0.4167": [21.41, 0, 0],
						"0.4583": [21.97, 0, 0],
						"0.5": [22.59, 0, 0],
						"0.5417": [23.26, 0, 0],
						"0.5833": [23.96, 0, 0],
						"0.625": [24.69, 0, 0],
						"0.6667": [25.42, 0, 0],
						"0.7083": [26.14, 0, 0],
						"0.75": [26.85, 0, 0],
						"0.7917": [27.53, 0, 0],
						"0.8333": [28.16, 0, 0],
						"0.875": [28.74, 0, 0],
						"0.9167": [29.25, 0, 0],
						"0.9583": [29.67, 0, 0],
						"1.0": [30, 0, 0]
					}
				},
				"knee_right": {
					"rotation": {
						"0.0": [10, 0, 0],
						"0.0417": [10, 0, 0],
						"0.0833": [10, 0, 0],
						"0.125": [10, 0, 0],
						"0.1667": [10, 0, 0],
						"0.2083": [10, 0, 0],
						"0.25": [10, 0, 0],
						"0.2917": [10, 0, 0],
						"0.3333": [10, 0, 0],
						"0.375": [10, 0, 0],
						"0.4167": [10, 0, 0],
						"0.4583": [10, 0, 0],
						"0.5": [10, 0, 0],
						"0.5417": [10, 0, 0],
						"0.5833": [10, 0, 0],
						"0.625": [10, 0, 0],
						"0.6667": [10, 0, 0],
						"0.7083": [10, 0, 0],
						"0.75": [10, 0, 0],
						"0.7917": [10, 0, 0],
						"0.8333": [10, 0, 0],
						"0.875": [10, 0, 0],
						"0.9167": [10, 0, 0],
						"0.9583": [10, 0, 0],
						"1.0": [10, 0, 0]
					}
				},
				"right_heel_joint": {
					"rotation": [-37.5, 0, 0]
				},
				"right_knee": {
					"rotation": [-15, 0, 0]
				},
				"right_leg_telescopic": {
					"position": {
						"0.0": [0, 0, -10],
						"0.0417": [0, 0, -11.33],
						"0.0833": [0, 0, -13.11],
						"0.125": [0, 0, -14],
						"0.1667": [0, 0, -13.98],
						"0.2083": [0, 0, -13.91],
						"0.25": [0, 0, -13.81],
						"0.2917": [0, 0, -13.68],
						"0.3333": [0, 0, -13.51],
						"0.375": [0, 0, -13.32],
						"0.4167": [0, 0, -13.11],
						"0.4583": [0, 0, -12.88],
						"0.5": [0, 0, -12.64],
						"0.5417": [0, 0, -12.38],
						"0.5833": [0, 0, -12.12],
						"0.625": [0, 0, -11.85],
						"0.6667": [0, 0, -11.59],
						"0.7083": [0, 0, -11.33],
						"0.75": [0, 0, -11.08],
						"0.7917": [0, 0, -10.85],
						"0.8333": [0, 0, -10.63],
						"0.875": [0, 0, -10.43],
						"0.9167": [0, 0, -10.26],
						"0.9583": [0, 0, -10.11],
						"1.0": [0, 0, -10]
					}
				},
				"right_outer_toe": {
					"rotation": [-15, 0, 0]
				},
				"right_inner_toe": {
					"rotation": [-15, 0, 0]
				},
				"right_foot": {
					"rotation": {
						"0.0": [-40, 0, 0],
						"0.0417": [-38.7, 0, 0],
						"0.0833": [-36.85, 0, 0],
						"0.125": [-35, 0, 0],
						"0.1667": [-32.78, 0, 0],
						"0.2083": [-30.56, 0, 0],
						"0.25": [-30, 0, 0],
						"0.2917": [-30.2, 0, 0],
						"0.3333": [-30.51, 0, 0],
						"0.375": [-30.91, 0, 0],
						"0.4167": [-31.41, 0, 0],
						"0.4583": [-31.97, 0, 0],
						"0.5": [-32.59, 0, 0],
						"0.5417": [-33.26, 0, 0],
						"0.5833": [-33.96, 0, 0],
						"0.625": [-34.69, 0, 0],
						"0.6667": [-35.42, 0, 0],
						"0.7083": [-36.14, 0, 0],
						"0.75": [-36.85, 0, 0],
						"0.7917": [-37.53, 0, 0],
						"0.8333": [-38.16, 0, 0],
						"0.875": [-38.74, 0, 0],
						"0.9167": [-39.25, 0, 0],
						"0.9583": [-39.67, 0, 0],
						"1.0": [-40, 0, 0]
					}
				}
			}
		},
		"animation.rex.activate": {
			"loop": "hold_on_last_frame",
			"animation_length": 5,
			"bones": {
				"main": {
					"position": {
						"0.0": [0, 0, 27],
						"0.125": [0, -0.19, 27.12],
						"0.25": [0, -0.5, 27.31],
						"0.375": [0, -0.56, 27.35],
						"0.5": [0, 0, 27],
						"0.625": [0, 1.63, 25.98],
						"0.75": [0, 4, 24.5],
						"0.875": [0, 6.38, 23.02],
						"1.0": [0, 8, 22],
						"1.125": [0, 8.19, 22.07],
						"1.25": [0, 7.5, 22.81],
						"1.375": [0, 7.06, 23.15],
						"1.5": [0, 8, 22],
						"1.625": [0, 11.25, 18.34],
						"1.75": [0, 16, 13],
						"1.875": [0, 20.75, 7.66],
						"2.0": [0, 24, 4],
						"2.125": [0, 24.82, 2.83],
						"2.25": [0, 24.19, 3.13],
						"2.375": [0, 23.46, 3.86],
						"2.5": [0, 24, 4],
						"2.625": [0, 26.64, 3.19],
						"2.75": [0, 30.5, 2],
						"2.875": [0, 34.36, 0.81],
						"3.0": [0, 37, 0],
						"3.125": [0, 37.91, -0.28],
						"3.25": [0, 37.81, -0.25],
						"3.375": [0, 37.3, -0.09],
						"3.5": [0, 37, 0],
						"3.625": [0, 37, 0],
						"3.75": [0, 37, 0],
						"3.875": [0, 37, 0],
						"4.0": [0, 37, 0]
					}
				},
				"body": {
					"rotation": {
						"0.0": [0, 0, 0],
						"0.125": [-0.32, 0, 0],
						"0.25": [-0.85, 0, 0],
						"0.375": [-0.96, 0, 0],
						"0.5": [0, 0, 0],
						"0.625": [2.76, 0, 0],
						"0.75": [6.81, 0, 0],
						"0.875": [10.85, 0, 0],
						"1.0": [13.61, 0, 0],
						"1.125": [14.57, 0, 0],
						"1.25": [14.46, 0, 0],
						"1.375": [13.93, 0, 0],
						"1.5": [13.61, 0, 0],
						"1.625": [13.61, 0, 0],
						"1.75": [13.61, 0, 0],
						"1.875": [13.61, 0, 0],
						"2.0": [13.61, 0, 0],
						"2.125": [13.93, 0, 0],
						"2.25": [14.46, 0, 0],
						"2.375": [14.57, 0, 0],
						"2.5": [13.61, 0, 0],
						"2.625": [10.85, 0, 0],
						"2.75": [6.81, 0, 0],
						"2.875": [2.76, 0, 0],
						"3.0": [0, 0, 0],
						"3.125": [-0.96, 0, 0],
						"3.25": [-0.85, 0, 0],
						"3.375": [-0.32, 0, 0],
						"3.5": [0, 0, 0],
						"3.625": [0, 0, 0],
						"3.75": [0, 0, 0],
						"3.875": [0, 0, 0],
						"4.0": [0, 0, 0]
					}
				},
				"weapon_pack": {
					"rotation": {
						"1.0": [0, 0, 0],
						"1.125": [0.18, 0, 0],
						"1.25": [0.47, 0, 0],
						"1.375": [0.53, 0, 0],
						"1.5": [0, 0, 0],
						"1.625": [-1.52, 0, 0],
						"1.75": [-3.75, 0, 0],
						"1.875": [-5.98, 0, 0],
						"2.0": [-7.5, 0, 0],
						"2.125": [-8.02, 0, 0],
						"2.25": [-7.94, 0, 0],
						"2.375": [-7.64, 0, 0],
						"2.5": [-7.5, 0, 0],
						"2.625": [-7.6, 0, 0],
						"2.75": [-7.73, 0, 0],
						"2.875": [-7.87, 0, 0],
						"3.0": [-7.97, 0, 0],
						"3.125": [-8.01, 0, 0],
						"3.25": [-8.03, 0, 0],
						"3.375": [-8.01, 0, 0],
						"3.5": [-7.97, 0, 0],
						"3.625": [-7.87, 0, 0],
						"3.75": [-7.73, 0, 0],
						"3.875": [-7.6, 0, 0],
						"4.0": [-7.5, 0, 0]
					}
				},
				"radome": {
					"rotation": {
						"0.0": [0, 0, 0],
						"0.125": [-0.07, 0, 0],
						"0.25": [-0.18, 0, 0],
						"0.375": [-0.21, 0, 0],
						"0.5": [0, 0, 0],
						"0.625": [0.6, 0, 0],
						"0.75": [1.48, 0, 0],
						"0.875": [2.36, 0, 0],
						"1.0": [2.96, 0, 0],
						"1.125": [3.07, 0, 0],
						"1.25": [2.89, 0, 0],
						"1.375": [2.74, 0, 0],
						"1.5": [2.96, 0, 0],
						"1.625": [3.79, 0, 0],
						"1.75": [5, 0, 0],
						"1.875": [6.21, 0, 0],
						"2.0": [7.04, 0, 0],
						"2.125": [7.26, 0, 0],
						"2.25": [7.11, 0, 0],
						"2.375": [6.93, 0, 0],
						"2.5": [7.04, 0, 0],
						"2.625": [7.64, 0, 0],
						"2.75": [8.52, 0, 0],
						"2.875": [9.4, 0, 0],
						"3.0": [10, 0, 0],
						"3.125": [10.21, 0, 0],
						"3.25": [10.19, 0, 0],
						"3.375": [10.07, 0, 0],
						"3.5": [10, 0, 0],
						"3.625": [10, 0, 0],
						"3.75": [10, 0, 0],
						"3.875": [10, 0, 0],
						"4.0": [10, 0, 0]
					}
				},
				"railgun": {
					"rotation": {
						"0.0": [0, 0, 0],
						"0.125": [0.07, 0.03, 0],
						"0.25": [0.19, 0.09, 0],
						"0.375": [0.21, 0.1, 0],
						"0.5": [0, 0, 0],
						"0.625": [-0.6, -0.3, 0],
						"0.75": [-1.48, -0.74, 0],
						"0.875": [-2.36, -1.18, 0],
						"1.0": [-2.96, -1.48, 0],
						"1.125": [-3.07, -1.54, 0],
						"1.25": [-2.89, -1.44, 0],
						"1.375": [-2.74, -1.37, 0],
						"1.5": [-2.96, -1.48, 0],
						"1.625": [-3.79, -1.89, 0],
						"1.75": [-5, -2.5, 0],
						"1.875": [-6.21, -3.11, 0],
						"2.0": [-7.04, -3.52, 0],
						"2.125": [-7.26, -3.63, 0],
						"2.25": [-7.11, -3.55, 0],
						"2.375": [-6.93, -3.46, 0],
						"2.5": [-7.04, -3.52, 0],
						"2.625": [-7.64, -3.82, 0],
						"2.75": [-8.52, -4.26, 0],
						"2.875": [-9.4, -4.7, 0],
						"3.0": [-10, -5, 0],
						"3.125": [-10.21, -5.1, 0],
						"3.25": [-10.18, -5.09, 0],
						"3.375": [-10.07, -5.03, 0],
						"3.5": [-10, -5, 0],
						"3.625": [-10, -5, 0],
						"3.75": [-10, -5, 0],
						"3.875": [-10, -5, 0],
						"4.0": [-10, -5, 0]
					}
				},
				"neck": {
					"rotation": {
						"0.0": [0, 0, 0],
						"0.125": [-0.12, 0, 0],
						"0.25": [-0.31, 0, 0],
						"0.375": [-0.35, 0, 0],
						"0.5": [0, 0, 0],
						"0.625": [0.26, 0, 0],
						"0.75": [0.6, 0, 0],
						"0.875": [1.02, 0, 0],
						"1.0": [1.48, 0, 0],
						"1.125": [1.98, 0, 0],
						"1.25": [2.5, 0, 0],
						"1.375": [3.02, 0, 0],
						"1.5": [3.52, 0, 0],
						"1.625": [3.98, 0, 0],
						"1.75": [4.4, 0, 0],
						"1.875": [4.74, 0, 0],
						"2.0": [5, 0, 0],
						"2.125": [5.35, 0, 0],
						"2.25": [5.31, 0, 0],
						"2.375": [5.12, 0, 0],
						"2.5": [5, 0, 0]
					}
				},
				"head": {
					"rotation": {
						"1.0": [0, 0, 0],
						"1.125": [-0.23, 0, 0],
						"1.25": [-0.62, 0, 0],
						"1.375": [-0.7, 0, 0],
						"1.5": [0, 0, 0],
						"1.625": [2.03, 0, 0],
						"1.75": [5, 0, 0],
						"1.875": [7.97, 0, 0],
						"2.0": [10, 0, 0],
						"2.125": [10.69, 0, 0],
						"2.25": [10.59, 0, 0],
						"2.375": [10.19, 0, 0],
						"2.5": [10, 0, 0],
						"2.625": [10.13, 0, 0],
						"2.75": [10.32, 0, 0],
						"2.875": [10.5, 0, 0],
						"3.0": [10.63, 0, 0],
						"3.125": [10.69, 0, 0],
						"3.25": [10.71, 0, 0],
						"3.375": [10.69, 0, 0],
						"3.5": [10.63, 0, 0],
						"3.625": [10.5, 0, 0],
						"3.75": [10.32, 0, 0],
						"3.875": [10.13, 0, 0],
						"4.0": [10, 0, 0]
					}
				},
				"left_thigh": {
					"rotation": {
						"0.0": [0, 0, 0],
						"0.125": [0, 0, 0],
						"0.25": [0, 0, 0],
						"0.375": [0, 0, 0],
						"0.5": [0, 0, 0],
						"0.625": [0, 0, 0],
						"0.75": [0, 0, 0],
						"0.875": [0, 0, 0],
						"1.0": [0, 0, 0],
						"1.125": [-0.47, 0, 0],
						"1.25": [-1.25, 0, 0],
						"1.375": [-1.41, 0, 0],
						"1.5": [0, 0, 0],
						"1.625": [4.06, 0, 0],
						"1.75": [10, 0, 0],
						"1.875": [15.94, 0, 0],
						"2.0": [20, 0, 0],
						"2.125": [21.17, 0, 0],
						"2.25": [20.63, 0, 0],
						"2.375": [19.77, 0, 0],
						"2.5": [20, 0, 0],
						"2.625": [22.03, 0, 0],
						"2.75": [25, 0, 0],
						"2.875": [27.97, 0, 0],
						"3.0": [30, 0, 0],
						"3.125": [30.7, 0, 0],
						"3.25": [30.63, 0, 0],
						"3.375": [30.23, 0, 0],
						"3.5": [30, 0, 0],
						"3.625": [30, 0, 0],
						"3.75": [30, 0, 0],
						"3.875": [30, 0, 0],
						"4.0": [30, 0, 0]
					}
				},
				"knee_left": {
					"rotation": {
						"0.0": [0, 0, 0],
						"0.125": [-0.23, 0, 0],
						"0.25": [-0.62, 0, 0],
						"0.375": [-0.7, 0, 0],
						"0.5": [0, 0, 0],
						"0.625": [2.03, 0, 0],
						"0.75": [5, 0, 0],
						"0.875": [7.97, 0, 0],
						"1.0": [10, 0, 0],
						"1.125": [10.69, 0, 0],
						"1.25": [10.58, 0, 0],
						"1.375": [10.18, 0, 0],
						"1.5": [10, 0, 0],
						"1.625": [10.15, 0, 0],
						"1.75": [10.37, 0, 0],
						"1.875": [10.59, 0, 0],
						"2.0": [10.74, 0, 0],
						"2.125": [10.8, 0, 0],
						"2.25": [10.81, 0, 0],
						"2.375": [10.78, 0, 0],
						"2.5": [10.74, 0, 0],
						"2.625": [10.66, 0, 0],
						"2.75": [10.56, 0, 0],
						"2.875": [10.45, 0, 0],
						"3.0": [10.37, 0, 0],
						"3.125": [10.35, 0, 0],
						"3.25": [10.37, 0, 0],
						"3.375": [10.39, 0, 0],
						"3.5": [10.37, 0, 0],
						"3.625": [10.29, 0, 0],
						"3.75": [10.18, 0, 0],
						"3.875": [10.08, 0, 0],
						"4.0": [10, 0, 0]
					}
				},
				"left_leg": {
					"rotation": {
						"0.0": [0, 0, 0],
						"0.125": [0, 0, 0],
						"0.25": [0, 0, 0],
						"0.375": [0, 0, 0],
						"0.5": [0, 0, 0],
						"0.625": [0, 0, 0],
						"0.75": [0, 0, 0],
						"0.875": [0, 0, 0],
						"1.0": [0, 0, 0],
						"1.125": [0, 0, 0],
						"1.25": [0, 0, 0],
						"1.375": [0, 0, 0],
						"1.5": [0, 0, 0],
						"1.625": [0, 0, 0],
						"1.75": [0, 0, 0],
						"1.875": [0, 0, 0],
						"2.0": [0, 0, 0],
						"2.125": [0, 0, 0],
						"2.25": [0, 0, 0],
						"2.375": [0, 0, 0],
						"2.5": [0, 0, 0],
						"2.625": [0, 0, 0],
						"2.75": [0, 0, 0],
						"2.875": [0, 0, 0],
						"3.0": [0, 0, 0],
						"3.125": [0, 0, 0],
						"3.25": [0, 0, 0],
						"3.375": [0, 0, 0],
						"3.5": [0, 0, 0],
						"3.625": [0, 0, 0],
						"3.75": [0, 0, 0],
						"3.875": [0, 0, 0],
						"4.0": [0, 0, 0]
					}
				},
				"left_heel_joint": {
					"rotation": {
						"0.0": [0, 0, 0],
						"0.125": [0.44, 0, 0],
						"0.25": [1.17, 0, 0],
						"0.375": [1.32, 0, 0],
						"0.5": [0, 0, 0],
						"0.625": [-3.81, 0, 0],
						"0.75": [-9.37, 0, 0],
						"0.875": [-14.94, 0, 0],
						"1.0": [-18.75, 0, 0],
						"1.125": [-19.63, 0, 0],
						"1.25": [-18.75, 0, 0],
						"1.375": [-17.87, 0, 0],
						"1.5": [-18.75, 0, 0],
						"1.625": [-22.56, 0, 0],
						"1.75": [-28.12, 0, 0],
						"1.875": [-33.69, 0, 0],
						"2.0": [-37.5, 0, 0],
						"2.125": [-38.76, 0, 0],
						"2.25": [-38.53, 0, 0],
						"2.375": [-37.77, 0, 0],
						"2.5": [-37.5, 0, 0],
						"2.625": [-37.98, 0, 0],
						"2.75": [-38.67, 0, 0],
						"2.875": [-39.36, 0, 0],
						"3.0": [-39.84, 0, 0],
						"3.125": [-40.06, 0, 0],
						"3.25": [-40.13, 0, 0],
						"3.375": [-40.06, 0, 0],
						"3.5": [-39.84, 0, 0],
						"3.625": [-39.36, 0, 0],
						"3.75": [-38.67, 0, 0],
						"3.875": [-37.98, 0, 0],
						"4.0": [-37.5, 0, 0]
					}
				},
				"left_knee": {
					"rotation": {
						"0.0": [0, 0, 0],
						"0.125": [0.18, 0, 0],
						"0.25": [0.47, 0, 0],
						"0.375": [0.53, 0, 0],
						"0.5": [0, 0, 0],
						"0.625": [-1.52, 0, 0],
						"0.75": [-3.75, 0, 0],
						"0.875": [-5.98, 0, 0],
						"1.0": [-7.5, 0, 0],
						"1.125": [-7.85, 0, 0],
						"1.25": [-7.5, 0, 0],
						"1.375": [-7.15, 0, 0],
						"1.5": [-7.5, 0, 0],
						"1.625": [-9.02, 0, 0],
						"1.75": [-11.25, 0, 0],
						"1.875": [-13.48, 0, 0],
						"2.0": [-15, 0, 0],
						"2.125": [-15.51, 0, 0],
						"2.25": [-15.41, 0, 0],
						"2.375": [-15.11, 0, 0],
						"2.5": [-15, 0, 0],
						"2.625": [-15.19, 0, 0],
						"2.75": [-15.47, 0, 0],
						"2.875": [-15.75, 0, 0],
						"3.0": [-15.94, 0, 0],
						"3.125": [-16.03, 0, 0],
						"3.25": [-16.06, 0, 0],
						"3.375": [-16.03, 0, 0],
						"3.5": [-15.94, 0, 0],
						"3.625": [-15.75, 0, 0],
						"3.75": [-15.47, 0, 0],
						"3.875": [-15.19, 0, 0],
						"4.0": [-15, 0, 0]
					}
				},
				"left_leg_telescopic": {
					"position": {
						"0.0": [0, 0, 0],
						"0.125": [0, 0, -0.01],
						"0.25": [0, 0, -0.04],
						"0.375": [0, 0, -0.04],
						"0.5": [0, 0, 0],
						"0.625": [0, 0, 0.13],
						"0.75": [0, 0, 0.32],
						"0.875": [0, 0, 0.5],
						"1.0": [0, 0, 0.63],
						"1.125": [0, 0, 0.69],
						"1.25": [0, 0, 0.71],
						"1.375": [0, 0, 0.69],
						"1.5": [0, 0, 0.63],
						"1.625": [0, 0, 0.5],
						"1.75": [0, 0, 0.31],
						"1.875": [0, 0, 0.13],
						"2.0": [0, 0, 0],
						"2.125": [0, 0, 0.19],
						"2.25": [0, 0, 0.59],
						"2.375": [0, 0, 0.69],
						"2.5": [0, 0, 0],
						"2.625": [0, 0, -2.03],
						"2.75": [0, 0, -5],
						"2.875": [0, 0, -7.97],
						"3.0": [0, 0, -10],
						"3.125": [0, 0, -10.7],
						"3.25": [0, 0, -10.62],
						"3.375": [0, 0, -10.23],
						"3.5": [0, 0, -10],
						"3.625": [0, 0, -10],
						"3.75": [0, 0, -10],
						"3.875": [0, 0, -10],
						"4.0": [0, 0, -10]
					}
				},
				"left_outer_toe": {
					"rotation": {
						"0.0": [0, 0, 0],
						"0.125": [0.1, 0, 0],
						"0.25": [0.28, 0, 0],
						"0.375": [0.31, 0, 0],
						"0.5": [0, 0, 0],
						"0.625": [-0.9, 0, 0],
						"0.75": [-2.22, 0, 0],
						"0.875": [-3.54, 0, 0],
						"1.0": [-4.44, 0, 0],
						"1.125": [-4.61, 0, 0],
						"1.25": [-4.34, 0, 0],
						"1.375": [-4.11, 0, 0],
						"1.5": [-4.44, 0, 0],
						"1.625": [-5.68, 0, 0],
						"1.75": [-7.5, 0, 0],
						"1.875": [-9.32, 0, 0],
						"2.0": [-10.56, 0, 0],
						"2.125": [-10.89, 0, 0],
						"2.25": [-10.66, 0, 0],
						"2.375": [-10.39, 0, 0],
						"2.5": [-10.56, 0, 0],
						"2.625": [-11.46, 0, 0],
						"2.75": [-12.78, 0, 0],
						"2.875": [-14.1, 0, 0],
						"3.0": [-15, 0, 0],
						"3.125": [-15.31, 0, 0],
						"3.25": [-15.28, 0, 0],
						"3.375": [-15.1, 0, 0],
						"3.5": [-15, 0, 0],
						"3.625": [-15, 0, 0],
						"3.75": [-15, 0, 0],
						"3.875": [-15, 0, 0],
						"4.0": [-15, 0, 0]
					}
				},
				"left_inner_toe": {
					"rotation": {
						"0.0": [0, 0, 0],
						"0.125": [0.1, 0, 0],
						"0.25": [0.28, 0, 0],
						"0.375": [0.31, 0, 0],
						"0.5": [0, 0, 0],
						"0.625": [-0.9, 0, 0],
						"0.75": [-2.22, 0, 0],
						"0.875": [-3.54, 0, 0],
						"1.0": [-4.44, 0, 0],
						"1.125": [-4.61, 0, 0],
						"1.25": [-4.34, 0, 0],
						"1.375": [-4.11, 0, 0],
						"1.5": [-4.44, 0, 0],
						"1.625": [-5.68, 0, 0],
						"1.75": [-7.5, 0, 0],
						"1.875": [-9.32, 0, 0],
						"2.0": [-10.56, 0, 0],
						"2.125": [-10.89, 0, 0],
						"2.25": [-10.66, 0, 0],
						"2.375": [-10.39, 0, 0],
						"2.5": [-10.56, 0, 0],
						"2.625": [-11.46, 0, 0],
						"2.75": [-12.78, 0, 0],
						"2.875": [-14.1, 0, 0],
						"3.0": [-15, 0, 0],
						"3.125": [-15.31, 0, 0],
						"3.25": [-15.28, 0, 0],
						"3.375": [-15.1, 0, 0],
						"3.5": [-15, 0, 0],
						"3.625": [-15, 0, 0],
						"3.75": [-15, 0, 0],
						"3.875": [-15, 0, 0],
						"4.0": [-15, 0, 0]
					}
				},
				"left_foot": {
					"rotation": {
						"0.0": [0, 0, 0],
						"0.125": [0.23, 0, 0],
						"0.25": [0.63, 0, 0],
						"0.375": [0.7, 0, 0],
						"0.5": [0, 0, 0],
						"0.625": [-2.03, 0, 0],
						"0.75": [-5, 0, 0],
						"0.875": [-7.97, 0, 0],
						"1.0": [-10, 0, 0],
						"1.125": [-10.23, 0, 0],
						"1.25": [-9.37, 0, 0],
						"1.375": [-8.83, 0, 0],
						"1.5": [-10, 0, 0],
						"1.625": [-14.06, 0, 0],
						"1.75": [-20, 0, 0],
						"1.875": [-25.94, 0, 0],
						"2.0": [-30, 0, 0],
						"2.125": [-31.17, 0, 0],
						"2.25": [-30.62, 0, 0],
						"2.375": [-29.77, 0, 0],
						"2.5": [-30, 0, 0],
						"2.625": [-32.03, 0, 0],
						"2.75": [-35, 0, 0],
						"2.875": [-37.97, 0, 0],
						"3.0": [-40, 0, 0],
						"3.125": [-40.7, 0, 0],
						"3.25": [-40.62, 0, 0],
						"3.375": [-40.23, 0, 0],
						"3.5": [-40, 0, 0],
						"3.625": [-40, 0, 0],
						"3.75": [-40, 0, 0],
						"3.875": [-40, 0, 0],
						"4.0": [-40, 0, 0]
					}
				},
				"right_thigh": {
					"rotation": {
						"0.0": [0, 0, 0],
						"0.125": [0, 0, 0],
						"0.25": [0, 0, 0],
						"0.375": [0, 0, 0],
						"0.5": [0, 0, 0],
						"0.625": [0, 0, 0],
						"0.75": [0, 0, 0],
						"0.875": [0, 0, 0],
						"1.0": [0, 0, 0],
						"1.125": [-0.47, 0, 0],
						"1.25": [-1.25, 0, 0],
						"1.375": [-1.41, 0, 0],
						"1.5": [0, 0, 0],
						"1.625": [4.06, 0, 0],
						"1.75": [10, 0, 0],
						"1.875": [15.94, 0, 0],
						"2.0": [20, 0, 0],
						"2.125": [21.17, 0, 0],
						"2.25": [20.63, 0, 0],
						"2.375": [19.77, 0, 0],
						"2.5": [20, 0, 0],
						"2.625": [22.03, 0, 0],
						"2.75": [25, 0, 0],
						"2.875": [27.97, 0, 0],
						"3.0": [30, 0, 0],
						"3.125": [30.7, 0, 0],
						"3.25": [30.63, 0, 0],
						"3.375": [30.23, 0, 0],
						"3.5": [30, 0, 0],
						"3.625": [30, 0, 0],
						"3.75": [30, 0, 0],
						"3.875": [30, 0, 0],
						"4.0": [30, 0, 0]
					}
				},
				"knee_right": {
					"rotation": {
						"0.0": [0, 0, 0],
						"0.125": [-0.23, 0, 0],
						"0.25": [-0.62, 0, 0],
						"0.375": [-0.7, 0, 0],
						"0.5": [0, 0, 0],
						"0.625": [2.03, 0, 0],
						"0.75": [5, 0, 0],
						"0.875": [7.97, 0, 0],
						"1.0": [10, 0, 0],
						"1.125": [10.69, 0, 0],
						"1.25": [10.58, 0, 0],
						"1.375": [10.18, 0, 0],
						"1.5": [10, 0, 0],
						"1.625": [10.15, 0, 0],
						"1.75": [10.37, 0, 0],
						"1.875": [10.59, 0, 0],
						"2.0": [10.74, 0, 0],
						"2.125": [10.8, 0, 0],
						"2.25": [10.81, 0, 0],
						"2.375": [10.78, 0, 0],
						"2.5": [10.74, 0, 0],
						"2.625": [10.66, 0, 0],
						"2.75": [10.56, 0, 0],
						"2.875": [10.45, 0, 0],
						"3.0": [10.37, 0, 0],
						"3.125": [10.35, 0, 0],
						"3.25": [10.37, 0, 0],
						"3.375": [10.39, 0, 0],
						"3.5": [10.37, 0, 0],
						"3.625": [10.29, 0, 0],
						"3.75": [10.18, 0, 0],
						"3.875": [10.08, 0, 0],
						"4.0": [10, 0, 0]
					}
				},
				"right_heel_joint": {
					"rotation": {
						"0.0": [0, 0, 0],
						"0.125": [0.44, 0, 0],
						"0.25": [1.17, 0, 0],
						"0.375": [1.32, 0, 0],
						"0.5": [0, 0, 0],
						"0.625": [-3.81, 0, 0],
						"0.75": [-9.37, 0, 0],
						"0.875": [-14.94, 0, 0],
						"1.0": [-18.75, 0, 0],
						"1.125": [-19.63, 0, 0],
						"1.25": [-18.75, 0, 0],
						"1.375": [-17.87, 0, 0],
						"1.5": [-18.75, 0, 0],
						"1.625": [-22.56, 0, 0],
						"1.75": [-28.12, 0, 0],
						"1.875": [-33.69, 0, 0],
						"2.0": [-37.5, 0, 0],
						"2.125": [-38.76, 0, 0],
						"2.25": [-38.53, 0, 0],
						"2.375": [-37.77, 0, 0],
						"2.5": [-37.5, 0, 0],
						"2.625": [-37.98, 0, 0],
						"2.75": [-38.67, 0, 0],
						"2.875": [-39.36, 0, 0],
						"3.0": [-39.84, 0, 0],
						"3.125": [-40.06, 0, 0],
						"3.25": [-40.13, 0, 0],
						"3.375": [-40.06, 0, 0],
						"3.5": [-39.84, 0, 0],
						"3.625": [-39.36, 0, 0],
						"3.75": [-38.67, 0, 0],
						"3.875": [-37.98, 0, 0],
						"4.0": [-37.5, 0, 0]
					}
				},
				"right_knee": {
					"rotation": {
						"0.0": [0, 0, 0],
						"0.125": [0.18, 0, 0],
						"0.25": [0.47, 0, 0],
						"0.375": [0.53, 0, 0],
						"0.5": [0, 0, 0],
						"0.625": [-1.52, 0, 0],
						"0.75": [-3.75, 0, 0],
						"0.875": [-5.98, 0, 0],
						"1.0": [-7.5, 0, 0],
						"1.125": [-7.85, 0, 0],
						"1.25": [-7.5, 0, 0],
						"1.375": [-7.15, 0, 0],
						"1.5": [-7.5, 0, 0],
						"1.625": [-9.02, 0, 0],
						"1.75": [-11.25, 0, 0],
						"1.875": [-13.48, 0, 0],
						"2.0": [-15, 0, 0],
						"2.125": [-15.51, 0, 0],
						"2.25": [-15.41, 0, 0],
						"2.375": [-15.11, 0, 0],
						"2.5": [-15, 0, 0],
						"2.625": [-15.19, 0, 0],
						"2.75": [-15.47, 0, 0],
						"2.875": [-15.75, 0, 0],
						"3.0": [-15.94, 0, 0],
						"3.125": [-16.03, 0, 0],
						"3.25": [-16.06, 0, 0],
						"3.375": [-16.03, 0, 0],
						"3.5": [-15.94, 0, 0],
						"3.625": [-15.75, 0, 0],
						"3.75": [-15.47, 0, 0],
						"3.875": [-15.19, 0, 0],
						"4.0": [-15, 0, 0]
					}
				},
				"right_leg_telescopic": {
					"position": {
						"0.0": [0, 0, 0],
						"0.125": [0, 0, -0.01],
						"0.25": [0, 0, -0.04],
						"0.375": [0, 0, -0.04],
						"0.5": [0, 0, 0],
						"0.625": [0, 0, 0.13],
						"0.75": [0, 0, 0.32],
						"0.875": [0, 0, 0.5],
						"1.0": [0, 0, 0.63],
						"1.125": [0, 0, 0.69],
						"1.25": [0, 0, 0.71],
						"1.375": [0, 0, 0.69],
						"1.5": [0, 0, 0.63],
						"1.625": [0, 0, 0.5],
						"1.75": [0, 0, 0.31],
						"1.875": [0, 0, 0.13],
						"2.0": [0, 0, 0],
						"2.125": [0, 0, 0.19],
						"2.25": [0, 0, 0.59],
						"2.375": [0, 0, 0.69],
						"2.5": [0, 0, 0],
						"2.625": [0, 0, -2.03],
						"2.75": [0, 0, -5],
						"2.875": [0, 0, -7.97],
						"3.0": [0, 0, -10],
						"3.125": [0, 0, -10.7],
						"3.25": [0, 0, -10.62],
						"3.375": [0, 0, -10.23],
						"3.5": [0, 0, -10],
						"3.625": [0, 0, -10],
						"3.75": [0, 0, -10],
						"3.875": [0, 0, -10],
						"4.0": [0, 0, -10]
					}
				},
				"right_outer_toe": {
					"rotation": {
						"0.0": [0, 0, 0],
						"0.125": [0.1, 0, 0],
						"0.25": [0.28, 0, 0],
						"0.375": [0.31, 0, 0],
						"0.5": [0, 0, 0],
						"0.625": [-0.9, 0, 0],
						"0.75": [-2.22, 0, 0],
						"0.875": [-3.54, 0, 0],
						"1.0": [-4.44, 0, 0],
						"1.125": [-4.61, 0, 0],
						"1.25": [-4.34, 0, 0],
						"1.375": [-4.11, 0, 0],
						"1.5": [-4.44, 0, 0],
						"1.625": [-5.68, 0, 0],
						"1.75": [-7.5, 0, 0],
						"1.875": [-9.32, 0, 0],
						"2.0": [-10.56, 0, 0],
						"2.125": [-10.89, 0, 0],
						"2.25": [-10.66, 0, 0],
						"2.375": [-10.39, 0, 0],
						"2.5": [-10.56, 0, 0],
						"2.625": [-11.46, 0, 0],
						"2.75": [-12.78, 0, 0],
						"2.875": [-14.1, 0, 0],
						"3.0": [-15, 0, 0],
						"3.125": [-15.31, 0, 0],
						"3.25": [-15.28, 0, 0],
						"3.375": [-15.1, 0, 0],
						"3.5": [-15, 0, 0],
						"3.625": [-15, 0, 0],
						"3.75": [-15, 0, 0],
						"3.875": [-15, 0, 0],
						"4.0": [-15, 0, 0]
					}
				},
				"right_inner_toe": {
					"rotation": {
						"0.0": [0, 0, 0],
						"0.125": [0.1, 0, 0],
						"0.25": [0.28, 0, 0],
						"0.375": [0.31, 0, 0],
						"0.5": [0, 0, 0],
						"0.625": [-0.9, 0, 0],
						"0.75": [-2.22, 0, 0],
						"0.875": [-3.54, 0, 0],
						"1.0": [-4.44, 0, 0],
						"1.125": [-4.61, 0, 0],
						"1.25": [-4.34, 0, 0],
						"1.375": [-4.11, 0, 0],
						"1.5": [-4.44, 0, 0],
						"1.625": [-5.68, 0, 0],
						"1.75": [-7.5, 0, 0],
						"1.875": [-9.32, 0, 0],
						"2.0": [-10.56, 0, 0],
						"2.125": [-10.89, 0, 0],
						"2.25": [-10.66, 0, 0],
						"2.375": [-10.39, 0, 0],
						"2.5": [-10.56, 0, 0],
						"2.625": [-11.46, 0, 0],
						"2.75": [-12.78, 0, 0],
						"2.875": [-14.1, 0, 0],
						"3.0": [-15, 0, 0],
						"3.125": [-15.31, 0, 0],
						"3.25": [-15.28, 0, 0],
						"3.375": [-15.1, 0, 0],
						"3.5": [-15, 0, 0],
						"3.625": [-15, 0, 0],
						"3.75": [-15, 0, 0],
						"3.875": [-15, 0, 0],
						"4.0": [-15, 0, 0]
					}
				},
				"right_foot": {
					"rotation": {
						"0.0": [0, 0, 0],
						"0.125": [0.23, 0, 0],
						"0.25": [0.63, 0, 0],
						"0.375": [0.7, 0, 0],
						"0.5": [0, 0, 0],
						"0.625": [-2.03, 0, 0],
						"0.75": [-5, 0, 0],
						"0.875": [-7.97, 0, 0],
						"1.0": [-10, 0, 0],
						"1.125": [-10.23, 0, 0],
						"1.25": [-9.37, 0, 0],
						"1.375": [-8.83, 0, 0],
						"1.5": [-10, 0, 0],
						"1.625": [-14.06, 0, 0],
						"1.75": [-20, 0, 0],
						"1.875": [-25.94, 0, 0],
						"2.0": [-30, 0, 0],
						"2.125": [-31.17, 0, 0],
						"2.25": [-30.62, 0, 0],
						"2.375": [-29.77, 0, 0],
						"2.5": [-30, 0, 0],
						"2.625": [-32.03, 0, 0],
						"2.75": [-35, 0, 0],
						"2.875": [-37.97, 0, 0],
						"3.0": [-40, 0, 0],
						"3.125": [-40.7, 0, 0],
						"3.25": [-40.62, 0, 0],
						"3.375": [-40.23, 0, 0],
						"3.5": [-40, 0, 0],
						"3.625": [-40, 0, 0],
						"3.75": [-40, 0, 0],
						"3.875": [-40, 0, 0],
						"4.0": [-40, 0, 0]
					}
				}
			}
		},
		"animation.rex.upright": {
			"loop": true,
			"bones": {
				"main": {
					"position": [0, 37, 0]
				},
				"body": {
					"rotation": [0, 0, 0]
				},
				"weapon_pack": {
					"rotation": [-7.5, 0, 0]
				},
				"radome": {
					"rotation": [10, 0, 0]
				},
				"railgun": {
					"rotation": [-10, -5, 0]
				},
				"neck": {
					"rotation": [5, 0, 0]
				},
				"head": {
					"rotation": [10, 0, 0]
				},
				"left_thigh": {
					"rotation": [30, 0, 0]
				},
				"knee_left": {
					"rotation": [10, 0, 0]
				},
				"left_leg": {
					"rotation": [0, 0, 0]
				},
				"left_heel_joint": {
					"rotation": [-37.5, 0, 0]
				},
				"left_knee": {
					"rotation": [-15, 0, 0]
				},
				"left_leg_telescopic": {
					"position": [0, 0, -10]
				},
				"left_outer_toe": {
					"rotation": [-15, 0, 0]
				},
				"left_inner_toe": {
					"rotation": [-17.5, 0, 0]
				},
				"left_foot": {
					"rotation": [-40, 0, 0]
				},
				"right_thigh": {
					"rotation": [30, 0, 0]
				},
				"knee_right": {
					"rotation": [10, 0, 0]
				},
				"right_heel_joint": {
					"rotation": [-37.5, 0, 0]
				},
				"right_knee": {
					"rotation": [-15, 0, 0]
				},
				"right_leg_telescopic": {
					"position": [0, 0, -10]
				},
				"right_outer_toe": {
					"rotation": [-15, 0, 0]
				},
				"right_inner_toe": {
					"rotation": [-15, 0, 0]
				},
				"right_foot": {
					"rotation": [-40, 0, 0]
				}
			}
		},
		"animation.rex.attack": {
			"loop": true,
			"animation_length": 0.5,
			"bones": {
				"main": {
					"position": [0, 37, 0]
				},
				"body": {
					"rotation": [0, 0, 0]
				},
				"weapon_pack": {
					"rotation": [-7.5, 0, 0]
				},
				"radome": {
					"rotation": [10, 0, 0]
				},
				"railgun": {
					"rotation": [-10, -5, 0]
				},
				"neck": {
					"rotation": [5, 0, 0]
				},
				"head": {
					"rotation": [10, 0, 0]
				},
				"left_thigh": {
					"rotation": [30, 0, 0]
				},
				"knee_left": {
					"rotation": [10, 0, 0]
				},
				"left_leg": {
					"rotation": [0, 0, 0]
				},
				"left_heel_joint": {
					"rotation": [-37.5, 0, 0]
				},
				"left_knee": {
					"rotation": [-15, 0, 0]
				},
				"left_leg_telescopic": {
					"position": [0, 0, -10]
				},
				"left_outer_toe": {
					"rotation": [-15, 0, 0]
				},
				"left_inner_toe": {
					"rotation": [-17.5, 0, 0]
				},
				"left_foot": {
					"rotation": [-40, 0, 0]
				},
				"right_thigh": {
					"rotation": {
						"0.0": [30, 0, 0],
						"0.0833": [28.64, 0, 0],
						"0.1667": [26.71, 0, 0],
						"0.25": [25.23, 0, 0],
						"0.2917": [25, 0, 0],
						"0.3333": [25.44, 0, 0],
						"0.4167": [27.88, 0, 0],
						"0.5": [30, 0, 0]
					}
				},
				"knee_right": {
					"rotation": {
						"0.0": [10, 0, 0],
						"0.0833": [1.56, 0, 0],
						"0.1667": [-5, 0, 0],
						"0.5": [10, 0, 0]
					}
				},
				"right_heel_joint": {
					"rotation": [-37.5, 0, 0]
				},
				"right_knee": {
					"rotation": [-15, 0, 0]
				},
				"right_leg_telescopic": {
					"position": {
						"0.0": [0, 0, -10],
						"0.0833": [0, 0, -4.12],
						"0.1667": [0, 0, -1],
						"0.25": [0, 0, -17.11],
						"0.2917": [0, 0, -23],
						"0.3333": [0, 0, -22.43],
						"0.4167": [0, 0, -15.94],
						"0.5": [0, 0, -10]
					}
				},
				"right_outer_toe": {
					"rotation": [-15, 0, 0]
				},
				"right_inner_toe": {
					"rotation": [-15, 0, 0]
				},
				"right_foot": {
					"rotation": {
						"0.0": [-40, 0, 0],
						"0.0833": [-45.42, 0, 0],
						"0.1667": [-53.18, 0, 0],
						"0.25": [-59.07, 0, 0],
						"0.2917": [-60, 0, 0],
						"0.3333": [-58.24, 0, 0],
						"0.4167": [-48.48, 0, 0],
						"0.5": [-40, 0, 0]
					}
				},
				"right_leg": {
					"rotation": {
						"0.0": [0, 0, 0],
						"0.0833": [0, -4.17, 0],
						"0.1667": [0, -9.72, 0],
						"0.25": [0, -12.5, 0],
						"0.3333": [0, -9.72, 0],
						"0.4167": [0, -4.17, 0],
						"0.5": [0, 0, 0]
					}
				}
			}
		},
		"animation.rex.critical_damage": {
			"loop": "hold_on_last_frame",
			"animation_length": 3,
			"bones": {
				"main": {
					"position": {
						"0.0": [0, 37, 0],
						"0.125": [0, 36.78, -0.22],
						"0.25": [0, 36.5, -0.5],
						"0.375": [0, 36.16, -0.84],
						"0.5": [0, 35.78, -1.22],
						"0.625": [0, 35.37, -1.63],
						"0.75": [0, 34.93, -2.07],
						"0.875": [0, 34.47, -2.53],
						"1.0": [0, 34, -3],
						"1.125": [0, 33.53, -3.47],
						"1.25": [0, 33.07, -3.93],
						"1.375": [0, 32.63, -4.37],
						"1.5": [0, 32.22, -4.78],
						"1.625": [0, 31.84, -5.16],
						"1.75": [0, 31.5, -5.5],
						"1.875": [0, 31.22, -5.78],
						"2.0": [0, 31, -6],
						"2.125": [0, 30.71, -6.29],
						"2.25": [0, 30.58, -6.42],
						"2.375": [0, 30.56, -6.44],
						"2.5": [0, 30.63, -6.37],
						"2.625": [0, 30.74, -6.26],
						"2.75": [0, 30.86, -6.14],
						"2.875": [0, 30.96, -6.04],
						"3.0": [0, 31, -6]
					}
				},
				"body": {
					"rotation": {
						"0.0": [0, 0, 0],
						"0.125": [0.55, 0, 0],
						"0.25": [1.26, 0, 0],
						"0.375": [2.1, 0, 0],
						"0.5": [3.05, 0, 0],
						"0.625": [4.08, 0, 0],
						"0.75": [5.19, 0, 0],
						"0.875": [6.33, 0, 0],
						"1.0": [7.5, 0, 0],
						"1.125": [8.67, 0, 0],
						"1.25": [9.81, 0, 0],
						"1.375": [10.92, 0, 0],
						"1.5": [11.95, 0, 0],
						"1.625": [12.9, 0, 0],
						"1.75": [13.74, 0, 0],
						"1.875": [14.45, 0, 0],
						"2.0": [15, 0, 0],
						"3.0": {
							"post": [15, 0, 0],
							"lerp_mode": "catmullrom"
						}
					}
				},
				"weapon_pack": {
					"rotation": {
						"0.0": [-7.5, 0, 0],
						"0.125": [-8.05, 0, 0],
						"0.25": [-8.76, 0, 0],
						"0.375": [-9.6, 0, 0],
						"0.5": [-10.55, 0, 0],
						"0.625": [-11.58, 0, 0],
						"0.75": [-12.69, 0, 0],
						"0.875": [-13.83, 0, 0],
						"1.0": [-15, 0, 0],
						"1.125": [-16.17, 0, 0],
						"1.25": [-17.31, 0, 0],
						"1.375": [-18.42, 0, 0],
						"1.5": [-19.45, 0, 0],
						"1.625": [-20.4, 0, 0],
						"1.75": [-21.24, 0, 0],
						"1.875": [-21.95, 0, 0],
						"2.0": [-22.5, 0, 0],
						"2.125": [-23.22, 0, 0],
						"2.25": [-23.55, 0, 0],
						"2.375": [-23.6, 0, 0],
						"2.5": [-23.44, 0, 0],
						"2.625": [-23.16, 0, 0],
						"2.75": [-22.85, 0, 0],
						"2.875": [-22.6, 0, 0],
						"3.0": [-22.5, 0, 0]
					}
				},
				"radome": {
					"rotation": {
						"0.0": [10, 0, 0],
						"0.125": [10.65, 0, 0],
						"0.25": [11.47, 0, 0],
						"0.375": [12.45, 0, 0],
						"0.5": [13.55, 0, 0],
						"0.625": [14.76, 0, 0],
						"0.75": [16.05, 0, 0],
						"0.875": [17.39, 0, 0],
						"1.0": [18.75, 0, 0],
						"1.125": [20.11, 0, 0],
						"1.25": [21.45, 0, 0],
						"1.375": [22.74, 0, 0],
						"1.5": [23.95, 0, 0],
						"1.625": [25.05, 0, 0],
						"1.75": [26.03, 0, 0],
						"1.875": [26.85, 0, 0],
						"2.0": [27.5, 0, 0],
						"2.125": [28.34, 0, 0],
						"2.25": [28.73, 0, 0],
						"2.375": [28.78, 0, 0],
						"2.5": [28.59, 0, 0],
						"2.625": [28.27, 0, 0],
						"2.75": [27.91, 0, 0],
						"2.875": [27.62, 0, 0],
						"3.0": [27.5, 0, 0]
					}
				},
				"railgun": {
					"rotation": {
						"0.0": [-10, -5, 0],
						"0.125": [-9.08, -5, 0],
						"0.25": [-7.9, -5, 0],
						"0.375": [-6.5, -5, 0],
						"0.5": [-4.92, -5, 0],
						"0.625": [-3.19, -5, 0],
						"0.75": [-1.36, -5, 0],
						"0.875": [0.55, -5, 0],
						"1.0": [2.5, -5, 0],
						"1.125": [4.45, -5, 0],
						"1.25": [6.36, -5, 0],
						"1.375": [8.19, -5, 0],
						"1.5": [9.92, -5, 0],
						"1.625": [11.5, -5, 0],
						"1.75": [12.9, -5, 0],
						"1.875": [14.08, -5, 0],
						"2.0": [15, -5, 0],
						"2.125": [16.2, -5, 0],
						"2.25": [16.76, -5, 0],
						"2.375": [16.83, -5, 0],
						"2.5": [16.56, -5, 0],
						"2.625": [16.1, -5, 0],
						"2.75": [15.59, -5, 0],
						"2.875": [15.17, -5, 0],
						"3.0": [15, -5, 0]
					}
				},
				"neck": {
					"rotation": [5, 0, 0]
				},
				"head": {
					"rotation": {
						"0.0": [10, 0, 0],
						"0.125": [10.65, 0, 0],
						"0.25": [11.47, 0, 0],
						"0.375": [12.45, 0, 0],
						"0.5": [13.55, 0, 0],
						"0.625": [14.76, 0, 0],
						"0.75": [16.05, 0, 0],
						"0.875": [17.39, 0, 0],
						"1.0": [18.75, 0, 0],
						"1.125": [20.11, 0, 0],
						"1.25": [21.45, 0, 0],
						"1.375": [22.74, 0, 0],
						"1.5": [23.95, 0, 0],
						"1.625": [25.05, 0, 0],
						"1.75": [26.03, 0, 0],
						"1.875": [26.85, 0, 0],
						"2.0": [27.5, 0, 0],
						"2.125": [28.34, 0, 0],
						"2.25": [28.73, 0, 0],
						"2.375": [28.78, 0, 0],
						"2.5": [28.59, 0, 0],
						"2.625": [28.27, 0, 0],
						"2.75": [27.91, 0, 0],
						"2.875": [27.62, 0, 0],
						"3.0": [27.5, 0, 0]
					}
				},
				"left_thigh": {
					"rotation": {
						"0.0": [30, 0, 0],
						"0.125": [30.37, 0, 0],
						"0.25": [30.84, 0, 0],
						"0.375": [31.4, 0, 0],
						"0.5": [32.03, 0, 0],
						"0.625": [32.72, 0, 0],
						"0.75": [33.46, 0, 0],
						"0.875": [34.22, 0, 0],
						"1.0": [35, 0, 0],
						"1.125": [35.78, 0, 0],
						"1.25": [36.54, 0, 0],
						"1.375": [37.28, 0, 0],
						"1.5": [37.97, 0, 0],
						"1.625": [38.6, 0, 0],
						"1.75": [39.16, 0, 0],
						"1.875": [39.63, 0, 0],
						"2.0": [40, 0, 0],
						"2.125": [40.48, 0, 0],
						"2.25": [40.7, 0, 0],
						"2.375": [40.73, 0, 0],
						"2.5": [40.63, 0, 0],
						"2.625": [40.44, 0, 0],
						"2.75": [40.23, 0, 0],
						"2.875": [40.07, 0, 0],
						"3.0": [40, 0, 0]
					}
				},
				"knee_left": {
					"rotation": {
						"0.0": [10, 0, 0],
						"0.125": [9.63, 0, 0],
						"0.25": [9.16, 0, 0],
						"0.375": [8.6, 0, 0],
						"0.5": [7.97, 0, 0],
						"0.625": [7.28, 0, 0],
						"0.75": [6.54, 0, 0],
						"0.875": [5.78, 0, 0],
						"1.0": [5, 0, 0],
						"1.125": [4.22, 0, 0],
						"1.25": [3.46, 0, 0],
						"1.375": [2.72, 0, 0],
						"1.5": [2.03, 0, 0],
						"1.625": [1.4, 0, 0],
						"1.75": [0.84, 0, 0],
						"1.875": [0.37, 0, 0],
						"2.0": [0, 0, 0],
						"2.125": [-0.48, 0, 0],
						"2.25": [-0.7, 0, 0],
						"2.375": [-0.73, 0, 0],
						"2.5": [-0.62, 0, 0],
						"2.625": [-0.44, 0, 0],
						"2.75": [-0.23, 0, 0],
						"2.875": [-0.07, 0, 0],
						"3.0": [0, 0, 0]
					}
				},
				"left_leg": {
					"rotation": [0, 0, 0]
				},
				"left_heel_joint": {
					"rotation": [-37.5, 0, 0]
				},
				"left_knee": {
					"rotation": [-15, 0, 0]
				},
				"left_leg_telescopic": {
					"position": {
						"0.0": [0, 0, -10],
						"0.125": [0, 0, -9.74],
						"0.25": [0, 0, -9.41],
						"0.375": [0, 0, -9.02],
						"0.5": [0, 0, -8.58],
						"0.625": [0, 0, -8.09],
						"0.75": [0, 0, -7.58],
						"0.875": [0, 0, -7.05],
						"1.0": [0, 0, -6.5],
						"1.125": [0, 0, -5.95],
						"1.25": [0, 0, -5.42],
						"1.375": [0, 0, -4.91],
						"1.5": [0, 0, -4.42],
						"1.625": [0, 0, -3.98],
						"1.75": [0, 0, -3.59],
						"1.875": [0, 0, -3.26],
						"2.0": [0, 0, -3],
						"2.125": [0, 0, -2.67],
						"2.25": [0, 0, -2.51],
						"2.375": [0, 0, -2.49],
						"2.5": [0, 0, -2.56],
						"2.625": [0, 0, -2.69],
						"2.75": [0, 0, -2.84],
						"2.875": [0, 0, -2.95],
						"3.0": [0, 0, -3]
					}
				},
				"left_outer_toe": {
					"rotation": [-15, 0, 0]
				},
				"left_inner_toe": {
					"rotation": [-17.5, 0, 0]
				},
				"left_foot": {
					"rotation": [-40, 0, 0]
				},
				"right_thigh": {
					"rotation": {
						"0.0": [30, 0, 0],
						"0.125": [30.37, 0, 0],
						"0.25": [30.84, 0, 0],
						"0.375": [31.4, 0, 0],
						"0.5": [32.03, 0, 0],
						"0.625": [32.72, 0, 0],
						"0.75": [33.46, 0, 0],
						"0.875": [34.22, 0, 0],
						"1.0": [35, 0, 0],
						"1.125": [35.78, 0, 0],
						"1.25": [36.54, 0, 0],
						"1.375": [37.28, 0, 0],
						"1.5": [37.97, 0, 0],
						"1.625": [38.6, 0, 0],
						"1.75": [39.16, 0, 0],
						"1.875": [39.63, 0, 0],
						"2.0": [40, 0, 0],
						"2.125": [40.48, 0, 0],
						"2.25": [40.7, 0, 0],
						"2.375": [40.73, 0, 0],
						"2.5": [40.63, 0, 0],
						"2.625": [40.44, 0, 0],
						"2.75": [40.23, 0, 0],
						"2.875": [40.07, 0, 0],
						"3.0": [40, 0, 0]
					}
				},
				"knee_right": {
					"rotation": {
						"0.0": [10, 0, 0],
						"0.125": [9.63, 0, 0],
						"0.25": [9.16, 0, 0],
						"0.375": [8.6, 0, 0],
						"0.5": [7.97, 0, 0],
						"0.625": [7.28, 0, 0],
						"0.75": [6.54, 0, 0],
						"0.875": [5.78, 0, 0],
						"1.0": [5, 0, 0],
						"1.125": [4.22, 0, 0],
						"1.25": [3.46, 0, 0],
						"1.375": [2.72, 0, 0],
						"1.5": [2.03, 0, 0],
						"1.625": [1.4, 0, 0],
						"1.75": [0.84, 0, 0],
						"1.875": [0.37, 0, 0],
						"2.0": [0, 0, 0],
						"2.125": [-0.48, 0, 0],
						"2.25": [-0.7, 0, 0],
						"2.375": [-0.73, 0, 0],
						"2.5": [-0.62, 0, 0],
						"2.625": [-0.44, 0, 0],
						"2.75": [-0.23, 0, 0],
						"2.875": [-0.07, 0, 0],
						"3.0": [0, 0, 0]
					}
				},
				"right_heel_joint": {
					"rotation": [-37.5, 0, 0]
				},
				"right_knee": {
					"rotation": [-15, 0, 0]
				},
				"right_leg_telescopic": {
					"position": {
						"0.0": [0, 0, -10],
						"0.125": [0, 0, -9.74],
						"0.25": [0, 0, -9.41],
						"0.375": [0, 0, -9.02],
						"0.5": [0, 0, -8.58],
						"0.625": [0, 0, -8.09],
						"0.75": [0, 0, -7.58],
						"0.875": [0, 0, -7.05],
						"1.0": [0, 0, -6.5],
						"1.125": [0, 0, -5.95],
						"1.25": [0, 0, -5.42],
						"1.375": [0, 0, -4.91],
						"1.5": [0, 0, -4.42],
						"1.625": [0, 0, -3.98],
						"1.75": [0, 0, -3.59],
						"1.875": [0, 0, -3.26],
						"2.0": [0, 0, -3],
						"2.125": [0, 0, -2.67],
						"2.25": [0, 0, -2.51],
						"2.375": [0, 0, -2.49],
						"2.5": [0, 0, -2.56],
						"2.625": [0, 0, -2.69],
						"2.75": [0, 0, -2.84],
						"2.875": [0, 0, -2.95],
						"3.0": [0, 0, -3]
					}
				},
				"right_outer_toe": {
					"rotation": [-15, 0, 0]
				},
				"right_inner_toe": {
					"rotation": [-15, 0, 0]
				},
				"right_foot": {
					"rotation": [-40, 0, 0]
				}
			}
		},
		"animation.rex.walk": {
			"loop": true,
			"animation_length": 2.75,
			"bones": {
				"main": {
					"position": {
						"0.0": [0, 37, 0],
						"0.0833": [0, 37, 0],
						"0.1667": [0, 37, 0],
						"0.25": [0, 37, 0],
						"0.3333": [0, 37, 0],
						"0.4167": [0, 37, 0],
						"0.5": [0, 37, 0],
						"0.5833": [0, 37, 0],
						"0.6667": [0, 37, 0],
						"0.75": [0, 37, 0],
						"0.8333": [0, 37, 0],
						"0.9167": [0, 37, 0],
						"1.0": [0, 37, 0],
						"1.0833": [0, 37, 0],
						"1.1667": [0, 37, 0],
						"1.25": [0, 37, 0],
						"1.3333": [0, 37, 0],
						"1.375": [0, 37, 0]
					}
				},
				"body": {
					"rotation": {
						"0.0": [0, 0, 0],
						"0.0833": [0.63, 0, 0],
						"0.1667": [1.48, 0, 0],
						"0.25": [2.52, 0, 0],
						"0.3333": [3.71, 0, 0],
						"0.4167": [5, 0, 0],
						"0.5": [6.36, 0, 0],
						"0.5833": [7.75, 0, 0],
						"0.6667": [9.12, 0, 0],
						"0.75": [10.44, 0, 0],
						"0.8333": [11.67, 0, 0],
						"0.9167": [12.76, 0, 0],
						"1.0": [13.68, 0, 0],
						"1.0833": [14.39, 0, 0],
						"1.1667": [14.84, 0, 0],
						"1.25": [15, 0, 0],
						"1.3333": [14.89, 0, 0],
						"1.4167": [14.57, 0, 0],
						"1.5": [14.06, 0, 0],
						"1.5833": [13.4, 0, 0],
						"1.6667": [12.59, 0, 0],
						"1.75": [11.67, 0, 0],
						"1.8333": [10.65, 0, 0],
						"1.9167": [9.57, 0, 0],
						"2.0": [8.44, 0, 0],
						"2.0833": [7.28, 0, 0],
						"2.1667": [6.13, 0, 0],
						"2.25": [5, 0, 0],
						"2.3333": [3.92, 0, 0],
						"2.4167": [2.9, 0, 0],
						"2.5": [1.98, 0, 0],
						"2.5833": [1.17, 0, 0],
						"2.6667": [0.51, 0, 0],
						"2.75": [0, 0, 0]
					}
				},
				"weapon_pack": {
					"rotation": {
						"0.0": [-7.5, 0, 0],
						"0.0833": [-8.13, 0, 0],
						"0.1667": [-8.98, 0, 0],
						"0.25": [-10.02, 0, 0],
						"0.3333": [-11.21, 0, 0],
						"0.4167": [-12.5, 0, 0],
						"0.5": [-13.86, 0, 0],
						"0.5833": [-15.25, 0, 0],
						"0.6667": [-16.62, 0, 0],
						"0.75": [-17.94, 0, 0],
						"0.8333": [-19.17, 0, 0],
						"0.9167": [-20.26, 0, 0],
						"1.0": [-21.18, 0, 0],
						"1.0833": [-21.89, 0, 0],
						"1.1667": [-22.34, 0, 0],
						"1.25": [-22.5, 0, 0],
						"1.3333": [-22.39, 0, 0],
						"1.4167": [-22.07, 0, 0],
						"1.5": [-21.56, 0, 0],
						"1.5833": [-20.9, 0, 0],
						"1.6667": [-20.09, 0, 0],
						"1.75": [-19.17, 0, 0],
						"1.8333": [-18.15, 0, 0],
						"1.9167": [-17.07, 0, 0],
						"2.0": [-15.94, 0, 0],
						"2.0833": [-14.78, 0, 0],
						"2.1667": [-13.63, 0, 0],
						"2.25": [-12.5, 0, 0],
						"2.3333": [-11.42, 0, 0],
						"2.4167": [-10.4, 0, 0],
						"2.5": [-9.48, 0, 0],
						"2.5833": [-8.67, 0, 0],
						"2.6667": [-8.01, 0, 0],
						"2.75": [-7.5, 0, 0]
					}
				},
				"radome": {
					"rotation": {
						"0.0": [10, 0, 0],
						"0.0833": [10, 0, 0],
						"0.1667": [10, 0, 0],
						"0.25": [10, 0, 0],
						"0.3333": [10, 0, 0],
						"0.4167": [10, 0, 0],
						"0.5": [10, 0, 0],
						"0.5833": [10, 0, 0],
						"0.6667": [10, 0, 0],
						"0.75": [10, 0, 0],
						"0.8333": [10, 0, 0],
						"0.9167": [10, 0, 0],
						"1.0": [10, 0, 0],
						"1.0833": [10, 0, 0],
						"1.1667": [10, 0, 0],
						"1.25": [10, 0, 0],
						"1.3333": [10, 0, 0],
						"1.375": [10, 0, 0]
					}
				},
				"railgun": {
					"rotation": [-10, -5, 0]
				},
				"neck": {
					"rotation": {
						"0.0": [5, 0, 0],
						"0.0833": [5, 0, 0],
						"0.1667": [5, 0, 0],
						"0.25": [5, 0, 0],
						"0.3333": [5, 0, 0],
						"0.4167": [5, 0, 0],
						"0.5": [5, 0, 0],
						"0.5833": [5, 0, 0],
						"0.6667": [5, 0, 0],
						"0.75": [5, 0, 0],
						"0.8333": [5, 0, 0],
						"0.9167": [5, 0, 0],
						"1.0": [5, 0, 0],
						"1.0833": [5, 0, 0],
						"1.1667": [5, 0, 0],
						"1.25": [5, 0, 0],
						"1.3333": [5, 0, 0],
						"1.375": [5, 0, 0]
					}
				},
				"head": {
					"rotation": {
						"0.0": [10, 0, 0],
						"0.0833": [9.58, 0, 0],
						"0.1667": [9.01, 0, 0],
						"0.25": [8.32, 0, 0],
						"0.3333": [7.53, 0, 0],
						"0.4167": [6.67, 0, 0],
						"0.5": [5.76, 0, 0],
						"0.5833": [4.84, 0, 0],
						"0.6667": [3.92, 0, 0],
						"0.75": [3.04, 0, 0],
						"0.8333": [2.22, 0, 0],
						"0.9167": [1.49, 0, 0],
						"1.0": [0.88, 0, 0],
						"1.0833": [0.41, 0, 0],
						"1.1667": [0.11, 0, 0],
						"1.25": [0, 0, 0],
						"1.3333": [0.07, 0, 0],
						"1.4167": [0.29, 0, 0],
						"1.5": [0.62, 0, 0],
						"1.5833": [1.07, 0, 0],
						"1.6667": [1.61, 0, 0],
						"1.75": [2.22, 0, 0],
						"1.8333": [2.9, 0, 0],
						"1.9167": [3.62, 0, 0],
						"2.0": [4.37, 0, 0],
						"2.0833": [5.14, 0, 0],
						"2.1667": [5.91, 0, 0],
						"2.25": [6.67, 0, 0],
						"2.3333": [7.39, 0, 0],
						"2.4167": [8.07, 0, 0],
						"2.5": [8.68, 0, 0],
						"2.5833": [9.22, 0, 0],
						"2.6667": [9.66, 0, 0],
						"2.75": [10, 0, 0]
					}
				},
				"left_thigh": {
					"rotation": {
						"0.0": [30, 0, 0],
						"0.0833": [33.15, 0, 0],
						"0.1667": [37.69, 0, 0],
						"0.25": [42.5, 0, 0],
						"0.3333": [47.31, 0, 0],
						"0.4167": [52.41, 0, 0],
						"0.5": [57.5, 0, 0],
						"0.5833": [62.59, 0, 0],
						"0.6667": [67.69, 0, 0],
						"0.75": [72.5, 0, 0],
						"0.8333": [77.5, 0, 0],
						"0.9167": [82.22, 0, 0],
						"1.0": [85, 0, 0],
						"1.0833": [85.19, 0, 0],
						"1.1667": [83.43, 0, 0],
						"1.25": [80, 0, 0],
						"1.3333": [74.26, 0, 0],
						"1.4167": [66.85, 0, 0],
						"1.5": [60, 0, 0],
						"1.5833": [54.91, 0, 0],
						"1.6667": [50.37, 0, 0],
						"1.75": [45, 0, 0],
						"1.8333": [36.94, 0, 0],
						"1.9167": [28.06, 0, 0],
						"2.0": [22.5, 0, 0],
						"2.0833": [22.1, 0, 0],
						"2.1667": [23.06, 0, 0],
						"2.25": [24.84, 0, 0],
						"2.3333": [26.94, 0, 0],
						"2.4167": [28.84, 0, 0],
						"2.5": [30, 0, 0]
					}
				},
				"knee_left": {
					"rotation": {
						"0.0": [10, 0, 0],
						"0.0833": [8.06, 0, 0],
						"0.1667": [5.28, 0, 0],
						"0.25": [2.5, 0, 0],
						"0.3333": [-0.19, 0, 0],
						"0.4167": [-2.87, 0, 0],
						"0.5": [-5, 0, 0],
						"0.5833": [-6.39, 0, 0],
						"0.6667": [-7.22, 0, 0],
						"0.75": [-7.5, 0, 0],
						"0.8333": [-6.85, 0, 0],
						"0.9167": [-5.65, 0, 0],
						"1.0": [-5, 0, 0],
						"1.0833": [-5.83, 0, 0],
						"1.1667": [-7.22, 0, 0],
						"1.25": [-7.5, 0, 0],
						"1.3333": [-7.09, 0, 0],
						"1.4167": [-6.46, 0, 0],
						"1.5": [-5.65, 0, 0],
						"1.5833": [-4.72, 0, 0],
						"1.6667": [-3.71, 0, 0],
						"1.75": [-2.69, 0, 0],
						"1.8333": [-1.69, 0, 0],
						"1.9167": [-0.78, 0, 0],
						"2.0": [0, 0, 0],
						"2.0833": [0.98, 0, 0],
						"2.1667": [1.85, 0, 0],
						"2.25": [2.66, 0, 0],
						"2.3333": [3.43, 0, 0],
						"2.4167": [4.2, 0, 0],
						"2.5": [5, 0, 0],
						"2.5833": [6.85, 0, 0],
						"2.6667": [8.7, 0, 0],
						"2.75": [10, 0, 0]
					}
				},
				"left_leg": {
					"rotation": [0, 0, 0]
				},
				"left_heel_joint": {
					"rotation": [-37.5, 0, 0]
				},
				"left_knee": {
					"rotation": [-15, 0, 0]
				},
				"left_leg_telescopic": {
					"position": {
						"0.0": [0, 0, -10],
						"0.0833": [0, 0, -9.19],
						"0.1667": [0, 0, -8.04],
						"0.25": [0, 0, -7],
						"0.3333": [0, 0, -6.37],
						"0.4167": [0, 0, -5.85],
						"0.5": [0, 0, -5],
						"0.5833": [0, 0, -3.37],
						"0.6667": [0, 0, -1.41],
						"0.75": [0, 0, 0],
						"0.8333": [0, 0, 0.23],
						"0.9167": [0, 0, 0.37],
						"1.0": [0, 0, 0.44],
						"1.0833": [0, 0, 0.45],
						"1.1667": [0, 0, 0.41],
						"1.25": [0, 0, 0.33],
						"1.3333": [0, 0, 0.23],
						"1.4167": [0, 0, 0.12],
						"1.5": [0, 0, 0],
						"1.5833": [0, 0, -0.41],
						"1.6667": [0, 0, -1.04],
						"1.75": [0, 0, -2],
						"1.8333": [0, 0, -3.33],
						"1.9167": [0, 0, -5],
						"2.0": [0, 0, -7],
						"2.0833": [0, 0, -9.93],
						"2.1667": [0, 0, -13.19],
						"2.25": [0, 0, -15],
						"2.3333": [0, 0, -14.86],
						"2.4167": [0, 0, -14.11],
						"2.5": [0, 0, -13],
						"2.5833": [0, 0, -11.78],
						"2.6667": [0, 0, -10.69],
						"2.75": [0, 0, -10]
					}
				},
				"left_outer_toe": {
					"rotation": {
						"0.0": [-15, 0, 0],
						"0.0833": [-15, 0, 0],
						"0.1667": [-15, 0, 0],
						"0.25": [-15, 0, 0],
						"0.3333": [-15, 0, 0],
						"0.4167": [-15, 0, 0],
						"0.5": [-15, 0, 0],
						"0.5833": [-15, 0, 0],
						"0.6667": [-15, 0, 0],
						"0.75": [-15, 0, 0],
						"0.8333": [-15, 0, 0],
						"0.9167": [-15, 0, 0],
						"1.0": [-15, 0, 0],
						"1.0833": [-15, 0, 0],
						"1.1667": [-15, 0, 0],
						"1.25": [-15, 0, 0],
						"1.3333": [-15, 0, 0],
						"1.375": [-15, 0, 0],
						"1.4167": [-15, 0, 0],
						"1.5": [-15, 0, 0],
						"1.5833": [-15, 0, 0],
						"1.6667": [-15, 0, 0],
						"1.75": [-15, 0, 0],
						"1.8333": [-15, 0, 0],
						"1.9167": [-15, 0, 0],
						"2.0": [-15, 0, 0],
						"2.0833": [-15, 0, 0],
						"2.1667": [-15, 0, 0],
						"2.25": [-15, 0, 0],
						"2.3333": [-15, 0, 0],
						"2.4167": [-15, 0, 0],
						"2.5": [-15, 0, 0],
						"2.5833": [-15, 0, 0],
						"2.6667": [-15, 0, 0],
						"2.75": [-15, 0, 0]
					}
				},
				"left_inner_toe": {
					"rotation": {
						"0.0": [-15, 0, 0],
						"0.0833": [-15, 0, 0],
						"0.1667": [-15, 0, 0],
						"0.25": [-15, 0, 0],
						"0.3333": [-15, 0, 0],
						"0.4167": [-15, 0, 0],
						"0.5": [-15, 0, 0],
						"0.5833": [-15, 0, 0],
						"0.6667": [-15, 0, 0],
						"0.75": [-15, 0, 0],
						"0.8333": [-15, 0, 0],
						"0.9167": [-15, 0, 0],
						"1.0": [-15, 0, 0],
						"1.0833": [-15, 0, 0],
						"1.1667": [-15, 0, 0],
						"1.25": [-15, 0, 0],
						"1.3333": [-15, 0, 0],
						"1.375": [-15, 0, 0],
						"1.4167": [-15, 0, 0],
						"1.5": [-15, 0, 0],
						"1.5833": [-15, 0, 0],
						"1.6667": [-15, 0, 0],
						"1.75": [-15, 0, 0],
						"1.8333": [-15, 0, 0],
						"1.9167": [-15, 0, 0],
						"2.0": [-15, 0, 0],
						"2.0833": [-15, 0, 0],
						"2.1667": [-15, 0, 0],
						"2.25": [-15, 0, 0],
						"2.3333": [-15, 0, 0],
						"2.4167": [-15, 0, 0],
						"2.5": [-15, 0, 0],
						"2.5833": [-15, 0, 0],
						"2.6667": [-15, 0, 0],
						"2.75": [-15, 0, 0]
					}
				},
				"left_foot": {
					"rotation": {
						"0.0": [-40, 0, 0],
						"0.0833": [-41.2, 0, 0],
						"0.1667": [-42.96, 0, 0],
						"0.25": [-45, 0, 0],
						"0.3333": [-48.33, 0, 0],
						"0.4167": [-51.94, 0, 0],
						"0.5": [-52.5, 0, 0],
						"0.5833": [-46.85, 0, 0],
						"0.6667": [-38.15, 0, 0],
						"0.75": [-32.5, 0, 0],
						"0.8333": [-32.18, 0, 0],
						"0.9167": [-32.72, 0, 0],
						"1.0": [-33.88, 0, 0],
						"1.0833": [-35.4, 0, 0],
						"1.1667": [-37.04, 0, 0],
						"1.25": [-38.54, 0, 0],
						"1.3333": [-39.66, 0, 0],
						"1.375": [-40, 0, 0],
						"1.4167": [-40.11, 0, 0],
						"1.5": [-40.28, 0, 0],
						"1.5833": [-40.41, 0, 0],
						"1.6667": [-40.49, 0, 0],
						"1.75": [-40.54, 0, 0],
						"1.8333": [-40.56, 0, 0],
						"1.9167": [-40.54, 0, 0],
						"2.0": [-40.51, 0, 0],
						"2.0833": [-40.45, 0, 0],
						"2.1667": [-40.39, 0, 0],
						"2.25": [-40.32, 0, 0],
						"2.3333": [-40.24, 0, 0],
						"2.4167": [-40.17, 0, 0],
						"2.5": [-40.1, 0, 0],
						"2.5833": [-40.05, 0, 0],
						"2.6667": [-40.01, 0, 0],
						"2.75": [-40, 0, 0]
					}
				},
				"right_thigh": {
					"rotation": {
						"0.0": [80, 0, 0],
						"0.0833": [74.33, 0, 0],
						"0.1667": [66.16, 0, 0],
						"0.25": [57.04, 0, 0],
						"0.3333": [48.53, 0, 0],
						"0.375": [45, 0, 0],
						"0.4167": [40.18, 0, 0],
						"0.5": [31.09, 0, 0],
						"0.5833": [24.37, 0, 0],
						"0.625": [22.5, 0, 0],
						"0.6667": [22.1, 0, 0],
						"0.75": [22.44, 0, 0],
						"0.8333": [23.88, 0, 0],
						"0.9167": [25.89, 0, 0],
						"1.0": [27.95, 0, 0],
						"1.0833": [29.54, 0, 0],
						"1.125": [30, 0, 0],
						"1.1667": [30.29, 0, 0],
						"1.25": [29.69, 0, 0],
						"1.3333": [29.36, 0, 0],
						"1.375": [30, 0, 0],
						"1.4167": [31.33, 0, 0],
						"1.5": [35.31, 0, 0],
						"1.5833": [40.13, 0, 0],
						"1.625": [42.5, 0, 0],
						"1.6667": [44.86, 0, 0],
						"1.75": [49.84, 0, 0],
						"1.8333": [54.97, 0, 0],
						"1.875": [57.5, 0, 0],
						"1.9167": [60.03, 0, 0],
						"2.0": [65.16, 0, 0],
						"2.0833": [70.14, 0, 0],
						"2.125": [72.5, 0, 0],
						"2.1667": [74.93, 0, 0],
						"2.25": [80, 0, 0],
						"2.3333": [83.96, 0, 0],
						"2.375": [85, 0, 0],
						"2.4167": [85.12, 0, 0],
						"2.5": [83.28, 0, 0],
						"2.5833": [80.75, 0, 0],
						"2.625": [80, 0, 0],
						"2.6667": [79.63, 0, 0],
						"2.75": [80, 0, 0]
					}
				},
				"knee_right": {
					"rotation": {
						"0.0": [-7.5, 0, 0],
						"0.0833": [-6.86, 0, 0],
						"0.1667": [-5.97, 0, 0],
						"0.25": [-4.92, 0, 0],
						"0.3333": [-3.77, 0, 0],
						"0.4167": [-2.59, 0, 0],
						"0.5": [-1.46, 0, 0],
						"0.5833": [-0.44, 0, 0],
						"0.625": [0, 0, 0],
						"0.6667": [0.5, 0, 0],
						"0.75": [1.43, 0, 0],
						"0.8333": [2.26, 0, 0],
						"0.9167": [3.04, 0, 0],
						"1.0": [3.81, 0, 0],
						"1.0833": [4.59, 0, 0],
						"1.125": [5, 0, 0],
						"1.1667": [5.98, 0, 0],
						"1.25": [8.28, 0, 0],
						"1.3333": [9.89, 0, 0],
						"1.375": [10, 0, 0],
						"1.4167": [9.47, 0, 0],
						"1.5": [7.03, 0, 0],
						"1.5833": [3.89, 0, 0],
						"1.625": [2.5, 0, 0],
						"1.6667": [1.19, 0, 0],
						"1.75": [-1.56, 0, 0],
						"1.8333": [-4.04, 0, 0],
						"1.875": [-5, 0, 0],
						"1.9167": [-5.76, 0, 0],
						"2.0": [-6.87, 0, 0],
						"2.0833": [-7.43, 0, 0],
						"2.125": [-7.5, 0, 0],
						"2.1667": [-7.31, 0, 0],
						"2.25": [-6.25, 0, 0],
						"2.3333": [-5.19, 0, 0],
						"2.375": [-5, 0, 0],
						"2.4167": [-5.16, 0, 0],
						"2.5": [-6.09, 0, 0],
						"2.5833": [-7.17, 0, 0],
						"2.625": [-7.5, 0, 0],
						"2.6667": [-7.69, 0, 0],
						"2.75": [-7.5, 0, 0]
					}
				},
				"right_heel_joint": {
					"rotation": {
						"0.0": [-37.5, 0, 0],
						"0.0833": [-37.5, 0, 0],
						"0.1667": [-37.5, 0, 0],
						"0.25": [-37.5, 0, 0],
						"0.3333": [-37.5, 0, 0],
						"0.4167": [-37.5, 0, 0],
						"0.5": [-37.5, 0, 0],
						"0.5833": [-37.5, 0, 0],
						"0.6667": [-37.5, 0, 0],
						"0.75": [-37.5, 0, 0],
						"0.8333": [-37.5, 0, 0],
						"0.9167": [-37.5, 0, 0],
						"1.0": [-37.5, 0, 0],
						"1.0833": [-37.5, 0, 0],
						"1.1667": [-37.5, 0, 0],
						"1.25": [-37.5, 0, 0],
						"1.3333": [-37.5, 0, 0],
						"1.375": [-37.5, 0, 0]
					}
				},
				"right_knee": {
					"rotation": {
						"0.0": [-15, 0, 0],
						"0.0833": [-15, 0, 0],
						"0.1667": [-15, 0, 0],
						"0.25": [-15, 0, 0],
						"0.3333": [-15, 0, 0],
						"0.4167": [-15, 0, 0],
						"0.5": [-15, 0, 0],
						"0.5833": [-15, 0, 0],
						"0.6667": [-15, 0, 0],
						"0.75": [-15, 0, 0],
						"0.8333": [-15, 0, 0],
						"0.9167": [-15, 0, 0],
						"1.0": [-15, 0, 0],
						"1.0833": [-15, 0, 0],
						"1.1667": [-15, 0, 0],
						"1.25": [-15, 0, 0],
						"1.3333": [-15, 0, 0],
						"1.375": [-15, 0, 0]
					}
				},
				"right_leg_telescopic": {
					"position": {
						"0.0": [0, 0, 0],
						"0.0833": [0, 0, 0.15],
						"0.125": [0, 0, 0],
						"0.1667": [0, 0, -0.18],
						"0.25": [0, 0, -0.69],
						"0.3333": [0, 0, -1.47],
						"0.375": [0, 0, -2],
						"0.4167": [0, 0, -2.62],
						"0.5": [0, 0, -4.12],
						"0.5833": [0, 0, -5.96],
						"0.625": [0, 0, -7],
						"0.6667": [0, 0, -8.31],
						"0.75": [0, 0, -11.62],
						"0.8333": [0, 0, -14.38],
						"0.875": [0, 0, -15],
						"0.9167": [0, 0, -15.03],
						"1.0": [0, 0, -14.62],
						"1.0833": [0, 0, -13.74],
						"1.1667": [0, 0, -12.6],
						"1.25": [0, 0, -11.41],
						"1.3333": [0, 0, -10.39],
						"1.375": [0, 0, -10],
						"1.4167": [0, 0, -9.37],
						"1.5": [0, 0, -8.31],
						"1.5833": [0, 0, -7.42],
						"1.625": [0, 0, -7],
						"1.6667": [0, 0, -6.64],
						"1.75": [0, 0, -6.13],
						"1.8333": [0, 0, -5.5],
						"1.875": [0, 0, -5],
						"1.9167": [0, 0, -4.28],
						"2.0": [0, 0, -2.38],
						"2.0833": [0, 0, -0.58],
						"2.125": [0, 0, 0],
						"2.1667": [0, 0, 0.15],
						"2.25": [0, 0, 0.32],
						"2.3333": [0, 0, 0.37],
						"2.4167": [0, 0, 0.33],
						"2.5": [0, 0, 0.24],
						"2.5833": [0, 0, 0.13],
						"2.6667": [0, 0, 0.04],
						"2.75": [0, 0, 0]
					}
				},
				"right_outer_toe": {
					"rotation": {
						"0.0": [-15, 0, 0],
						"0.0833": [-15, 0, 0],
						"0.1667": [-15, 0, 0],
						"0.25": [-15, 0, 0],
						"0.3333": [-15, 0, 0],
						"0.4167": [-15, 0, 0],
						"0.5": [-15, 0, 0],
						"0.5833": [-15, 0, 0],
						"0.6667": [-15, 0, 0],
						"0.75": [-15, 0, 0],
						"0.8333": [-15, 0, 0],
						"0.9167": [-15, 0, 0],
						"1.0": [-15, 0, 0],
						"1.0833": [-15, 0, 0],
						"1.1667": [-15, 0, 0],
						"1.25": [-15, 0, 0],
						"1.3333": [-15, 0, 0],
						"1.375": [-15, 0, 0],
						"1.4167": [-15, 0, 0],
						"1.5": [-15, 0, 0],
						"1.5833": [-15, 0, 0],
						"1.6667": [-15, 0, 0],
						"1.75": [-15, 0, 0],
						"1.8333": [-15, 0, 0],
						"1.9167": [-15, 0, 0],
						"2.0": [-15, 0, 0],
						"2.0833": [-15, 0, 0],
						"2.1667": [-15, 0, 0],
						"2.25": [-15, 0, 0],
						"2.3333": [-15, 0, 0],
						"2.4167": [-15, 0, 0],
						"2.5": [-15, 0, 0],
						"2.5833": [-15, 0, 0],
						"2.6667": [-15, 0, 0],
						"2.75": [-15, 0, 0]
					}
				},
				"right_inner_toe": {
					"rotation": {
						"0.0": [-15, 0, 0],
						"0.0833": [-15.09, 0, 0],
						"0.1667": [-15.22, 0, 0],
						"0.25": [-15.37, 0, 0],
						"0.3333": [-15.54, 0, 0],
						"0.4167": [-15.73, 0, 0],
						"0.5": [-15.94, 0, 0],
						"0.5833": [-16.14, 0, 0],
						"0.6667": [-16.35, 0, 0],
						"0.75": [-16.56, 0, 0],
						"0.8333": [-16.76, 0, 0],
						"0.9167": [-16.94, 0, 0],
						"1.0": [-17.11, 0, 0],
						"1.0833": [-17.25, 0, 0],
						"1.1667": [-17.37, 0, 0],
						"1.25": [-17.45, 0, 0],
						"1.3333": [-17.49, 0, 0],
						"1.375": [-17.5, 0, 0],
						"1.4167": [-17.49, 0, 0],
						"1.5": [-17.45, 0, 0],
						"1.5833": [-17.37, 0, 0],
						"1.6667": [-17.25, 0, 0],
						"1.75": [-17.11, 0, 0],
						"1.8333": [-16.94, 0, 0],
						"1.9167": [-16.76, 0, 0],
						"2.0": [-16.56, 0, 0],
						"2.0833": [-16.35, 0, 0],
						"2.1667": [-16.14, 0, 0],
						"2.25": [-15.94, 0, 0],
						"2.3333": [-15.73, 0, 0],
						"2.4167": [-15.54, 0, 0],
						"2.5": [-15.37, 0, 0],
						"2.5833": [-15.22, 0, 0],
						"2.6667": [-15.09, 0, 0],
						"2.75": [-15, 0, 0]
					}
				},
				"right_foot": {
					"rotation": {
						"0.0": [-32.5, 0, 0],
						"0.0833": [-32.76, 0, 0],
						"0.1667": [-33.07, 0, 0],
						"0.25": [-33.44, 0, 0],
						"0.3333": [-33.85, 0, 0],
						"0.4167": [-34.3, 0, 0],
						"0.5": [-34.78, 0, 0],
						"0.5833": [-35.28, 0, 0],
						"0.6667": [-35.81, 0, 0],
						"0.75": [-36.34, 0, 0],
						"0.8333": [-36.87, 0, 0],
						"0.9167": [-37.41, 0, 0],
						"1.0": [-37.93, 0, 0],
						"1.0833": [-38.44, 0, 0],
						"1.1667": [-38.93, 0, 0],
						"1.25": [-39.38, 0, 0],
						"1.3333": [-39.81, 0, 0],
						"1.375": [-40, 0, 0],
						"1.4167": [-40.95, 0, 0],
						"1.5": [-42.5, 0, 0],
						"1.5833": [-44.05, 0, 0],
						"1.625": [-45, 0, 0],
						"1.6667": [-46.42, 0, 0],
						"1.75": [-50.31, 0, 0],
						"1.8333": [-52.81, 0, 0],
						"1.875": [-52.5, 0, 0],
						"1.9167": [-50.53, 0, 0],
						"2.0": [-42.97, 0, 0],
						"2.0833": [-34.99, 0, 0],
						"2.125": [-32.5, 0, 0]
					}
				},
				"right_leg": {
					"rotation": [0, 0, 0]
				}
			}
		}
	}
}